polhemusFT/FTCmdIF.dll
polhemusFT/FTCmdIFD.dll
polhemusFT/FTCmdIFU.dll
polhemusFT/FTCmdIFUD.dll
polhemusFT/G4CmdIF.dll
polhemusFT/G4CmdIFD.dll
polhemusFT/G4CmdIFU.dll
polhemusFT/G4CmdIFUD.dll
polhemusFT/G4Track.dll
polhemusFT/PDI.dll
polhemusFT/PDID.dll
polhemusFT/PDIU.dll
polhemusFT/PDIUD.dll
polhemusFT/PiCmdIF.dll
polhemusFT/PiCmdIFD.dll
polhemusFT/PiCmdIFU.dll
polhemusFT/PiCmdIFUD.dll
polhemusFT/__init__.py
polhemusFT/_polhemusFT.pyd
polhemusFT-0.0.3.dist-info/LICENSE
polhemusFT-0.0.3.dist-info/METADATA
polhemusFT-0.0.3.dist-info/WHEEL
polhemusFT-0.0.3.dist-info/top_level.txt
polhemusFT-0.0.3.dist-info/RECORD
